LICENSE
README.md
questionary/__init__.py
questionary/constants.py
questionary/form.py
questionary/prompt.py
questionary/prompts/__init__.py
questionary/prompts/autocomplete.py
questionary/prompts/checkbox.py
questionary/prompts/common.py
questionary/prompts/confirm.py
questionary/prompts/password.py
questionary/prompts/path.py
questionary/prompts/rawselect.py
questionary/prompts/select.py
questionary/prompts/text.py
questionary/py.typed
questionary/question.py
questionary/utils.py
questionary/version.py
questionary-1.8.0.dist-info/LICENSE
questionary-1.8.0.dist-info/WHEEL
questionary-1.8.0.dist-info/METADATA
questionary-1.8.0.dist-info/RECORD
