Metadata-Version: 2.1
Name: questionary
Version: 1.8.0
Summary: Python library to build pretty command line user prompts ⭐️
Home-page: https://github.com/tmbo/questionary
License: MIT
Keywords: cli,ui,inquirer,questions,prompt
Author: Tom Bocklisch
Author-email: tombocklisch@gmail.com
Maintainer: Tom Bocklisch
Maintainer-email: tombocklisch@gmail.com
Requires-Python: >=3.6,<3.10
Classifier: Development Status :: 4 - Beta
Classifier: Intended Audience :: Developers
Classifier: License :: OSI Approved :: MIT License
Classifier: Programming Language :: Python
Classifier: Programming Language :: Python :: 3
Classifier: Programming Language :: Python :: 3.6
Classifier: Programming Language :: Python :: 3.7
Classifier: Programming Language :: Python :: 3.8
Classifier: Programming Language :: Python :: 3.9
Classifier: Topic :: Software Development :: Libraries
Requires-Dist: prompt_toolkit (>=2.0,<4.0)
Project-URL: Documentation, https://github.com/tmbo/questionary#documentation
Project-URL: Repository, https://github.com/tmbo/questionary
